hashdir/__init__.py
hashdir/__main__.py
hashdir/cli.py
hashdir/util_hash.py
hashdir/util_logging.py
hashdir/util_logic.py
hashdir-0.24.dist-info/LICENSE
hashdir-0.24.dist-info/METADATA
hashdir-0.24.dist-info/WHEEL
hashdir-0.24.dist-info/entry_points.txt
hashdir-0.24.dist-info/top_level.txt
hashdir-0.24.dist-info/RECORD
