Metadata-Version: 2.1
Name: hashdir
Version: 0.24
Summary: A command line tool to calculate hashes of directory trees using various hash algorithms.
Home-page: https://github.com/fcivaner/hashdir
Author: Fırat Civaner
Author-email: fcivaner@gmail.com
License: MIT License
Keywords: hash directory imohash md5
Platform: UNKNOWN
Classifier: Programming Language :: Python :: 3
Classifier: License :: OSI Approved :: MIT License
Classifier: Operating System :: OS Independent
Requires-Dist: imohash
